static_pages_client/__init__.py
static_pages_client/abstract.py
static_pages_client/static.py
static_pages_client-1.0.0.dist-info/LICENSE
static_pages_client-1.0.0.dist-info/METADATA
static_pages_client-1.0.0.dist-info/WHEEL
static_pages_client-1.0.0.dist-info/top_level.txt
static_pages_client-1.0.0.dist-info/RECORD
