Metadata-Version: 2.1
Name: static-pages-client
Version: 1.0.0
Summary: Static pages client is a package that helps working with Static Pages API easier.
Home-page: https://github.com/ebs-integrator/static-pages-client
Author: Dorin Musteata
Author-email: dorin.musteata@ebs-integrator.com
License: UNKNOWN
Project-URL: Bug Tracker, https://github.com/ebs-integrator/static-pages-client/issues
Platform: UNKNOWN
Classifier: Programming Language :: Python :: 3
Classifier: Programming Language :: Python :: 3.6
Classifier: Programming Language :: Python :: 3.7
Classifier: Programming Language :: Python :: 3.8
Classifier: Programming Language :: Python :: 3.9
Classifier: License :: OSI Approved :: MIT License
Classifier: Operating System :: OS Independent
Requires-Python: >=3.8
License-File: LICENSE
